ansible_deployer/main.py
ansible_deployer/modules/__init__.py
ansible_deployer/modules/globalvars.py
ansible_deployer/modules/configs/__init__.py
ansible_deployer/modules/configs/config.py
ansible_deployer/modules/configs/schema.py
ansible_deployer/modules/database/__init__.py
ansible_deployer/modules/database/creator.py
ansible_deployer/modules/database/schema.py
ansible_deployer/modules/database/writer.py
ansible_deployer/modules/locking/__init__.py
ansible_deployer/modules/locking/locking.py
ansible_deployer/modules/misc/arguments.py
ansible_deployer/modules/misc/utils.py
ansible_deployer/modules/outputs/__init__.py
ansible_deployer/modules/outputs/blocks.py
ansible_deployer/modules/outputs/formatting.py
ansible_deployer/modules/outputs/loggers.py
ansible_deployer/modules/runners/__init__.py
ansible_deployer/modules/runners/run.py
ansible_deployer/modules/validators/__init__.py
ansible_deployer/modules/validators/validate.py
ansible_deployer/plugins/log_plays_adjusted.py
ansible_deployer/plugins/sqlite_deployer.py
ansible_deployer-0.0.57.dist-info/licenses/LICENSE
ansible_deployer-0.0.57.dist-info/METADATA
ansible_deployer-0.0.57.dist-info/WHEEL
ansible_deployer-0.0.57.dist-info/entry_points.txt
ansible_deployer-0.0.57.dist-info/top_level.txt
ansible_deployer-0.0.57.dist-info/RECORD
