Metadata-Version: 2.4
Name: ansible-deployer
Version: 0.0.57
Summary: Wrapper around ansible-playbook allowing configurable tasks and permissions
Home-page: https://github.com/cinek810/ansible-deployer
Author: J. Wierzbowski, M. Stolarek
Author-email: 
License: MIT
Project-URL: Source, https://github.com/cinek810/ansible-deployer
Platform: linux
Classifier: Development Status :: 3 - Alpha
Classifier: Environment :: Console
Classifier: Intended Audience :: System Administrators
Classifier: License :: OSI Approved :: MIT License
Classifier: Natural Language :: English
Classifier: Operating System :: POSIX :: Linux
Classifier: Programming Language :: Python :: 3.6
Classifier: Programming Language :: Python :: 3.7
Classifier: Programming Language :: Python :: 3.8
Classifier: Programming Language :: Python :: 3.9
Classifier: Topic :: System :: Systems Administration
Classifier: Topic :: System :: Distributed Computing
Classifier: Topic :: System :: Clustering
Requires-Python: >=3.6
License-File: LICENSE
Requires-Dist: pyyaml>=5.3.1
Requires-Dist: cerberus>=1.3.1
Requires-Dist: pytest-testinfra>=6.6.0
Dynamic: license-file
